fish_feats/Analysis.py
fish_feats/Association.py
fish_feats/CellObjects.py
fish_feats/ClassifyCells.py
fish_feats/Configuration.py
fish_feats/DaskedEpyseg.py
fish_feats/FishGrid.py
fish_feats/FishWidgets.py
fish_feats/MainImage.py
fish_feats/NapaCells.py
fish_feats/NapaMix.py
fish_feats/NapaNuclei.py
fish_feats/NapaRNA.py
fish_feats/Naparing.py
fish_feats/ProcessFolder.py
fish_feats/RNASpots.py
fish_feats/SegmentObj.py
fish_feats/Separe.py
fish_feats/Utils.py
fish_feats/__init__.py
fish_feats/_button_grid.py
fish_feats/cellpose_dask.py
fish_feats/napari.yaml
fishfeats-1.2.12.dist-info/LICENSE
fishfeats-1.2.12.dist-info/METADATA
fishfeats-1.2.12.dist-info/WHEEL
fishfeats-1.2.12.dist-info/entry_points.txt
fishfeats-1.2.12.dist-info/top_level.txt
fishfeats-1.2.12.dist-info/RECORD
