Metadata-Version: 2.1
Name: fishfeats
Version: 1.2.12
Summary: Napari plugin for RNA-Fish+cells analysis pipeline
Author: Gaëlle Letort
License: BSD 3-Clause License
Project-URL: Bug Tracker, https://github.com/gletort/FishFeats/issues
Project-URL: Documentation, https://gletort.github.io/FishFeats/
Project-URL: Source Code, https://github.com/gletort/FishFeats
Project-URL: User Support, https://github.com/gletort/FishFeats/issues
Classifier: Framework :: napari
Classifier: Operating System :: OS Independent
Classifier: Programming Language :: Python
Classifier: Programming Language :: Python :: 3.9
Classifier: Programming Language :: Python :: 3.10
Classifier: Programming Language :: Python :: 3.11
Classifier: Programming Language :: Python :: 3.12
Classifier: Topic :: Scientific/Engineering :: Image Processing
Classifier: License :: OSI Approved :: BSD License
Requires-Python: >=3.7
License-File: LICENSE
Requires-Dist: big-fish>=0.6.2
Requires-Dist: pyqt5
Requires-Dist: imaris-ims-file-reader
Requires-Dist: czifile
Requires-Dist: tifffile
Requires-Dist: munkres
Requires-Dist: matplotlib
Requires-Dist: scikit-image
Requires-Dist: lxml
Requires-Dist: packaging
Requires-Dist: cellpose[distributed]
Requires-Dist: stardist
Requires-Dist: opencv-python-headless<4.12; python_version < "3.11"
Requires-Dist: pyqt6<6.10; python_version < "3.11"
Requires-Dist: epyseg; python_version < "3.11"
Requires-Dist: tensorflow<2.15; python_version < "3.11"
Requires-Dist: napari<0.6.4; python_version < "3.11"
Requires-Dist: numpy<=1.26; python_version < "3.11"
Requires-Dist: opencv-python-headless; python_version >= "3.11"
Requires-Dist: tensorflow; python_version >= "3.11"
Requires-Dist: napari; python_version >= "3.11"
Requires-Dist: numpy; python_version >= "3.11"
